mercutio/__init__.py
mercutio/_metadata.py
mercutio/_version.py
mercutio/defaults.py
mercutio-0.10.2.dist-info/LICENSE
mercutio-0.10.2.dist-info/METADATA
mercutio-0.10.2.dist-info/WHEEL
mercutio-0.10.2.dist-info/top_level.txt
mercutio-0.10.2.dist-info/RECORD
