Metadata-Version: 2.1
Name: mercutio
Version: 0.10.2
Summary: yet another character creation engine
Home-page: https://github.com/signebedi/mercutio
Author: Sig Janoska-Bedi
Author-email: signe@siftingwinnowing.com
License: MIT
Classifier: Programming Language :: Python :: 3
Classifier: License :: OSI Approved :: MIT License
Classifier: Operating System :: OS Independent
Requires-Python: >=3.6
License-File: LICENSE
Requires-Dist: pandas (<3.0.0,>=2.0.0)
Requires-Dist: pytest (<8.0.0,>=7.3.2)
